saltext/azurerm/__init__.py
saltext/azurerm/loader.py
saltext/azurerm/version.py
saltext/azurerm/clouds/__init__.py
saltext/azurerm/clouds/azurerm.py
saltext/azurerm/fileserver/__init__.py
saltext/azurerm/fileserver/azurefs.py
saltext/azurerm/modules/__init__.py
saltext/azurerm/modules/azurerm_compute.py
saltext/azurerm/modules/azurerm_compute_availability_set.py
saltext/azurerm/modules/azurerm_compute_disk.py
saltext/azurerm/modules/azurerm_compute_image.py
saltext/azurerm/modules/azurerm_compute_virtual_machine.py
saltext/azurerm/modules/azurerm_compute_virtual_machine_extension.py
saltext/azurerm/modules/azurerm_compute_virtual_machine_image.py
saltext/azurerm/modules/azurerm_dns.py
saltext/azurerm/modules/azurerm_keyvault_key.py
saltext/azurerm/modules/azurerm_keyvault_secret.py
saltext/azurerm/modules/azurerm_keyvault_vault.py
saltext/azurerm/modules/azurerm_network.py
saltext/azurerm/modules/azurerm_resource.py
saltext/azurerm/states/__init__.py
saltext/azurerm/states/azurerm_compute.py
saltext/azurerm/states/azurerm_compute_availability_set.py
saltext/azurerm/states/azurerm_compute_virtual_machine.py
saltext/azurerm/states/azurerm_dns.py
saltext/azurerm/states/azurerm_keyvault_key.py
saltext/azurerm/states/azurerm_keyvault_secret.py
saltext/azurerm/states/azurerm_keyvault_vault.py
saltext/azurerm/states/azurerm_network.py
saltext/azurerm/states/azurerm_resource.py
saltext/azurerm/utils/__init__.py
saltext/azurerm/utils/azurerm.py
saltext_azurerm-4.4.0.dist-info/LICENSE
saltext_azurerm-4.4.0.dist-info/METADATA
saltext_azurerm-4.4.0.dist-info/NOTICE
saltext_azurerm-4.4.0.dist-info/NOTICE.txt
saltext_azurerm-4.4.0.dist-info/WHEEL
saltext_azurerm-4.4.0.dist-info/entry_points.txt
saltext_azurerm-4.4.0.dist-info/top_level.txt
saltext_azurerm-4.4.0.dist-info/RECORD
