Metadata-Version: 2.2
Name: saltext.azurerm
Version: 4.4.0
Summary: Salt Extension for interacting with Microsoft Azure
Author-email: "EITR Technologies, LLC" <devops@eitr.tech>
License: Apache Software License
Project-URL: Homepage, https://github.com/salt-extensions/saltext-azurerm
Project-URL: Documentation, https://salt-extensions.github.io/saltext-azurerm/
Project-URL: Source, https://github.com/salt-extensions/saltext-azurerm
Project-URL: Tracker, https://github.com/salt-extensions/saltext-azurerm/issues
Keywords: salt-extension
Platform: any
Classifier: Programming Language :: Python
Classifier: Programming Language :: Cython
Classifier: Programming Language :: Python :: 3
Classifier: Programming Language :: Python :: 3 :: Only
Classifier: Programming Language :: Python :: 3.9
Classifier: Programming Language :: Python :: 3.10
Classifier: Development Status :: 4 - Beta
Classifier: Intended Audience :: Developers
Classifier: License :: OSI Approved :: Apache Software License
Requires-Python: >=3.9
License-File: LICENSE
License-File: NOTICE
License-File: NOTICE.txt
Requires-Dist: salt>=3006
Requires-Dist: azure-batch==12.0.0
Requires-Dist: azure-common==1.1.28
Requires-Dist: azure-graphrbac==0.61.1
Requires-Dist: azure-keyvault==4.2.0
Requires-Dist: azure-identity==1.10.0
Requires-Dist: azure-core==1.24.2
Requires-Dist: azure-mgmt-authorization==2.0.0
Requires-Dist: azure-mgmt-batch==16.2.0
Requires-Dist: azure-mgmt-compute==27.1.0
Requires-Dist: azure-mgmt-dns==8.0.0
Requires-Dist: azure-mgmt-privatedns==1.0.0
Requires-Dist: azure-mgmt-keyvault==10.1.0
Requires-Dist: azure-mgmt-monitor==6.0.1
Requires-Dist: azure-mgmt-msi==6.0.1
Requires-Dist: azure-mgmt-network==20.0.0
Requires-Dist: azure-mgmt-resource==21.1.0
Requires-Dist: azure-mgmt-storage==21.0.0
Requires-Dist: azure-mgmt-subscription==3.0.0
Requires-Dist: azure-mgmt-web==6.1.0
Requires-Dist: azure-storage-blob==12.12.0
Requires-Dist: azure-storage-common==2.1.0
Requires-Dist: azure-storage-file==2.1.0
Requires-Dist: azure-storage-nspkg==3.1.0
Requires-Dist: azure-storage-queue==12.3.0
Requires-Dist: msrest==0.7.1
Requires-Dist: msrestazure==0.6.4
Provides-Extra: changelog
Requires-Dist: towncrier==24.8.0; extra == "changelog"
Provides-Extra: dev
Requires-Dist: nox[uv]>=2024.3; extra == "dev"
Requires-Dist: pre-commit>=2.21.0; extra == "dev"
Provides-Extra: dev-extra
Requires-Dist: black==25.1.0; extra == "dev-extra"
Requires-Dist: isort==6.0.1; extra == "dev-extra"
Requires-Dist: coverage==7.7.1; extra == "dev-extra"
Provides-Extra: docs
Requires-Dist: sphinx; extra == "docs"
Requires-Dist: sphinx-prompt; extra == "docs"
Requires-Dist: sphinxcontrib-spelling; extra == "docs"
Requires-Dist: sphinx-copybutton; extra == "docs"
Requires-Dist: towncrier==24.8.0; extra == "docs"
Requires-Dist: sphinxcontrib-towncrier; extra == "docs"
Requires-Dist: myst_parser; extra == "docs"
Requires-Dist: furo; extra == "docs"
Requires-Dist: sphinx-inline-tabs; extra == "docs"
Provides-Extra: docsauto
Requires-Dist: sphinx-autobuild; extra == "docsauto"
Provides-Extra: lint
Requires-Dist: pylint==3.3.5; extra == "lint"
Provides-Extra: tests
Requires-Dist: pytest>=7.2.0; extra == "tests"
Requires-Dist: pytest-salt-factories>=1.0.0; extra == "tests"
Requires-Dist: pytest-instafail; extra == "tests"
Requires-Dist: pytest-ordering>=0.6; extra == "tests"
